nxtensor/__init__.py
nxtensor/assembly.py
nxtensor/exceptions.py
nxtensor/extraction.py
nxtensor/extractor.py
nxtensor/square_extractor.py
nxtensor/variable.py
nxtensor/variable_block_extraction.py
nxtensor/yaml_serializable.py
nxtensor/core/__init__.py
nxtensor/core/assembly.py
nxtensor/core/types.py
nxtensor/core/xarray_channel_extraction.py
nxtensor/core/xarray_extractions.py
nxtensor/tests/__init__.py
nxtensor/tests/create_era5_extraction.py
nxtensor/tests/create_era5_variables.py
nxtensor/utils/__init__.py
nxtensor/utils/coordinate_utils.py
nxtensor/utils/coordinates.py
nxtensor/utils/csv_option_names.py
nxtensor/utils/csv_utils.py
nxtensor/utils/db_types.py
nxtensor/utils/db_utils.py
nxtensor/utils/file_utils.py
nxtensor/utils/hdf5_utils.py
nxtensor/utils/image_utils.py
nxtensor/utils/interpolation_utils.py
nxtensor/utils/level_utils.py
nxtensor/utils/naming_utils.py
nxtensor/utils/tensor_dimensions.py
nxtensor/utils/time_resolutions.py
nxtensor/utils/time_utils.py
nxtensor/utils/xarray_rpn_calulator.py
NXTensor-0.3.4.0.dist-info/LICENSE
NXTensor-0.3.4.0.dist-info/METADATA
NXTensor-0.3.4.0.dist-info/WHEEL
NXTensor-0.3.4.0.dist-info/top_level.txt
NXTensor-0.3.4.0.dist-info/RECORD
