Metadata-Version: 2.1
Name: NXTensor
Version: 0.3.4.0
Summary: NXTensor is a tensor making framework based on Xarray. It automates the extraction of multichannel images (tensors) from NetCDF time series of geolocated data.
Home-page: 
Author: Sébastien Gardoll
Author-email: sebastien@gardoll.fr
Classifier: Programming Language :: Python :: 3
Classifier: License :: OSI Approved :: CEA CNRS Inria Logiciel Libre License, version 2.1 (CeCILL-2.1)
Classifier: Development Status :: 2 - Pre-Alpha
Classifier: Topic :: Scientific/Engineering
Classifier: Topic :: Scientific/Engineering :: Artificial Intelligence
Classifier: Topic :: Scientific/Engineering :: Image Recognition
Classifier: Operating System :: OS Independent
Requires-Python: >=3.7
License-File: LICENSE
Requires-Dist: dask (>=2.17.2)
Requires-Dist: h5py (>=2.10.0)
Requires-Dist: matplotlib (>=3.3.2)
Requires-Dist: netcdf4 (>=1.5.3)
Requires-Dist: numpy (>=1.18.1)
Requires-Dist: pandas (>=1.0.3)
Requires-Dist: pyyaml (>=5.3.1)
Requires-Dist: scikit-learn (>=0.22.1)
Requires-Dist: scipy (>=1.4.1)
Requires-Dist: xarray (>=0.15.1)
